main.py
bangumi_tv-0.1.3.dist-info/METADATA
bangumi_tv-0.1.3.dist-info/WHEEL
bangumi_tv-0.1.3.dist-info/entry_points.txt
bangumi_tv-0.1.3.dist-info/top_level.txt
bangumi_tv-0.1.3.dist-info/RECORD
