Metadata-Version: 2.4
Name: bangumi-tv
Version: 0.1.3
Summary: For Bangumi TV API MCP Service
Requires-Python: >=3.10
Requires-Dist: mcp[cli]>=1.6.0
Requires-Dist: requests>=2.32.3
Requires-Dist: httpx[socks]>=0.25.0
Requires-Dist: python-dotenv>=1.0.0
